[
  {
    "question": "What is the capital of France?",
    "answer": "Paris"
  },
    {
    "question": "What is the capital of Italy?",
    "answer": "Rome"
  },
  {
    "question": "When did World War II begin?",
    "answer": "1939"
  },
  {
    "question": "Who was the first emperor of Rome?",
    "answer": "Augustus"
  },
  {
    "question": "What year did the French Revolution start?",
    "answer": "1789"
  },
  {
    "question": "What are the four traditional periods of European history?",
    "answer": "Prehistoric Europe, classical antiquity, the Middle Ages, and the modern era"
  },
  {
    "question": "In which year is the fall of the Western Roman Empire traditionally dated?",
    "answer": "476 AD"
  },
  {
    "question": "Who was the Frankish king crowned as Roman Emperor in 800 AD?",
    "answer": "Charlemagne"
  },
  {
    "question": "What was the period of renewed interest in classical art and learning in Europe called?",
    "answer": "The Renaissance"
  },
  {
    "question": "What event is traditionally considered the start of the Reformation?",
    "answer": "The publication of the 95 Theses by Martin Luther in 1517"
  },
  {
    "question": "Who was the leader of Nazi Germany during World War II?",
    "answer": "Adolf Hitler"
  },
  {
    "question": "What was the peace treaty that ended World War I?",
    "answer": "The Treaty of Versailles"
  },
  {
    "question": "In what year was the Berlin Wall torn down?",
    "answer": "1989"
  },
  {
    "question": "Which ancient civilization built the palace at Knossos on Crete?",
    "answer": "The Minoan civilization"
  },
  {
    "question": "At which battle in 732 did the Franks stop the Muslim advance into Europe?",
    "answer": "The Battle of Tours (or Battle of Poitiers)"
  },
  {
    "question": "What was the name of the pandemic that killed a huge part of Europe's population in the 14th century?",
    "answer": "The Black Death (or bubonic plague)"
  },
  {
    "question": "With which war is Joan of Arc associated?",
    "answer": "The Hundred Years' War"
  },
  {
    "question": "Who wrote the famous political treatise, 'The Prince'?",
    "answer": "Niccolò Machiavelli"
  },
  {
    "question": "Which maritime republic was a major rival of Genoa and dominated trade in the Mediterranean?",
    "answer": "Venice"
  },
  {
    "question": "Which famous Florentine family were great patrons of the arts during the Renaissance?",
    "answer": "The Medici"
  },
  {
    "question": "Who was the leader of the 'Expedition of the Thousand' and a key figure in the unification of Italy?",
    "answer": "Giuseppe Garibaldi"
  },
  {
    "question": "In what year did Italy become a republic?",
    "answer": "1946"
  },
  {
    "question": "What was the name given by the Greeks to the Iberian Peninsula, after a river?",
    "answer": "Iberia"
  },
  {
    "question": "What was the Muslim-ruled area on the Iberian Peninsula called?",
    "answer": "Al-Andalus"
  },
  {
    "question": "In which year did Christopher Columbus first reach the Americas?",
    "answer": "1492"
  },
  {
    "question": "Which Spanish king ruled during the country's 'Golden Age' and was married to Mary Tudor?",
    "answer": "Philip II"
  },
  {
    "question": "What were the military campaigns to reconquer the Iberian Peninsula from the Moors called?",
    "answer": "The Reconquista"
  },
  {
    "question": "Which French king is known as the 'Sun King'?",
    "answer": "Louis XIV"
  },
  {
    "question": "In which year did the French Revolution begin?",
    "answer": "1789"
  },
  {
    "question": "Who was the famous French military leader and emperor who was finally defeated at Waterloo?",
    "answer": "Napoleon Bonaparte"
  },
  {
    "question": "What is the name of the famous painting by Leonardo da Vinci, housed in the Louvre?",
    "answer": "The Mona Lisa (or La Gioconda)"
  },
  {
    "question": "What invention by Johannes Gutenberg revolutionized the spread of knowledge?",
    "answer": "The printing press"
  },
  {
    "question": "To which artistic era did Michelangelo belong?",
    "answer": "The Renaissance"
  },
  {
    "question": "Which artistic style, known for its drama and grandeur, followed the Renaissance?",
    "answer": "Baroque"
  },
  {
    "question": "Who is the sculptor of the famous statue of 'David'?",
    "answer": "Michelangelo"
  },
  {
    "question": "What is the title of the famous 15th-century painting by Jan van Eyck depicting a couple?",
    "answer": "The Arnolfini Portrait"
  },
  {
    "question": "Which non-Indo-European people inhabited north-western Italy before the rise of Rome?",
    "answer": "The Etruscans"
  },
  {
    "question": "According to legend, in what year was Rome founded?",
    "answer": "753 BC"
  },
  {
    "question": "Which two powers fought in the Punic Wars?",
    "answer": "Rome and Carthage"
  },
  {
    "question": "Whose translation of the Bible was key to the development of the modern Standard German language?",
    "answer": "Martin Luther"
  },
  {
    "question": "The kingdom of which Germanic tribe formed the basis for the state in modern-day France?",
    "answer": "The Franks"
  },
  {
    "question": "What were the major military expeditions by European Christians to the Holy Land called?",
    "answer": "The Crusades"
  },
  {
    "question": "Which famous painting by Pablo Picasso depicts the horrors of the bombing of a town during the Spanish Civil War?",
    "answer": "Guernica"
  },
  {
    "question": "What was the name of the political regime led by Benito Mussolini in Italy?",
    "answer": "Fascism"
  }
]
